domain_model/__init__.py
domain_model/aggregate.py
domain_model/commands.py
domain_model/domain/__init__.py
domain_model/domain_events.py
domain_model/events_handlers.py
domain_model/object_id.py
domain_model/passport/__init__.py
domain_model/passport/passport.py
domain_model/passport/repository.py
domain_model/passport/use_case.py
domain_model/repository.py
domain_model/tests/__init__.py
domain_model/tests/command_runner.py
domain_model/typing.py
domain_model/unit_of_work/__init__.py
domain_model/unit_of_work/enums.py
domain_model/unit_of_work/typing.py
domain_model/unit_of_work/unit_of_work.py
domain_model/unit_of_work/units/__init__.py
domain_model/unit_of_work/units/base.py
domain_model/unit_of_work/units/cache/__init__.py
domain_model/unit_of_work/units/cache/base.py
domain_model/unit_of_work/units/cache/contrib/__init__.py
domain_model/unit_of_work/units/cache/contrib/aioredis.py
domain_model/unit_of_work/units/cache/in_memory.py
domain_model/unit_of_work/units/db/__init__.py
domain_model/unit_of_work/units/db/base.py
domain_model/unit_of_work/units/db/contrib/__init__.py
domain_model/unit_of_work/units/db/contrib/sqlalchemy.py
domain_model/use_case.py
a_domain_model-0.1.6.dist-info/LICENSE.md
a_domain_model-0.1.6.dist-info/METADATA
a_domain_model-0.1.6.dist-info/WHEEL
a_domain_model-0.1.6.dist-info/RECORD
