Metadata-Version: 2.3
Name: a-domain-model
Version: 0.1.6
Summary: 
License: MIT
Author: AndriiDubonos
Author-email: andreydubonos1@gmail.com
Requires-Python: >=3.13
Classifier: License :: OSI Approved :: MIT License
Classifier: Programming Language :: Python :: 3
Classifier: Programming Language :: Python :: 3.13
Requires-Dist: pydantic (==2.11.3)
